onnxruntime/LICENSE
onnxruntime/Privacy.md
onnxruntime/ThirdPartyNotices.txt
onnxruntime/__init__.py
onnxruntime/backend/__init__.py
onnxruntime/backend/backend.py
onnxruntime/backend/backend_rep.py
onnxruntime/capi/__init__.py
onnxruntime/capi/_ld_preload.py
onnxruntime/capi/_pybind_state.py
onnxruntime/capi/onnxruntime_collect_build_info.py
onnxruntime/capi/onnxruntime_inference_collection.py
onnxruntime/capi/onnxruntime_pybind11_state.so
onnxruntime/capi/onnxruntime_validation.py
onnxruntime/capi/training/__init__.py
onnxruntime/datasets/__init__.py
onnxruntime/datasets/logreg_iris.onnx
onnxruntime/datasets/mul_1.onnx
onnxruntime/datasets/sigmoid.onnx
onnxruntime/quantization/__init__.py
onnxruntime/quantization/calibrate.py
onnxruntime/quantization/onnx_model.py
onnxruntime/quantization/onnx_quantizer.py
onnxruntime/quantization/preprocess.py
onnxruntime/quantization/qdq_loss_debug.py
onnxruntime/quantization/qdq_quantizer.py
onnxruntime/quantization/quant_utils.py
onnxruntime/quantization/quantize.py
onnxruntime/quantization/registry.py
onnxruntime/quantization/shape_inference.py
onnxruntime/quantization/CalTableFlatBuffers/KeyValue.py
onnxruntime/quantization/CalTableFlatBuffers/TrtTable.py
onnxruntime/quantization/CalTableFlatBuffers/__init__.py
onnxruntime/quantization/operators/__init__.py
onnxruntime/quantization/operators/activation.py
onnxruntime/quantization/operators/argmax.py
onnxruntime/quantization/operators/attention.py
onnxruntime/quantization/operators/base_operator.py
onnxruntime/quantization/operators/binary_op.py
onnxruntime/quantization/operators/concat.py
onnxruntime/quantization/operators/conv.py
onnxruntime/quantization/operators/direct_q8.py
onnxruntime/quantization/operators/embed_layernorm.py
onnxruntime/quantization/operators/gather.py
onnxruntime/quantization/operators/gavgpool.py
onnxruntime/quantization/operators/gemm.py
onnxruntime/quantization/operators/lstm.py
onnxruntime/quantization/operators/matmul.py
onnxruntime_coreml-1.13.1.dist-info/METADATA
onnxruntime_coreml-1.13.1.dist-info/WHEEL
onnxruntime_coreml-1.13.1.dist-info/entry_points.txt
onnxruntime_coreml-1.13.1.dist-info/top_level.txt
onnxruntime_coreml-1.13.1.dist-info/RECORD
